{"results":[{"username":"Jono","message":"Do my bidding!"},{"username":"Eric","text":"hello","roomname":"lobby"},{"username":"Eric","text":"","roomname":"lobby"},{"username":"Eric","text":"Hi, my name is Eric","roomname":"lobby"},{"username":"Eric","text":"hello","roomname":"Me"},{"username":"Eric","text":"hi","roomname":"hello"},{"username":"Eric","text":"I am COOL","roomname":"lobby"},{"username":"Eric","text":"hello","roomname":"lobby"},{"username":"Eric","text":"hello there","roomname":"lobby"},{"username":"Eric","text":"hi!","roomname":"lobby"},{"username":"Eric","text":"me","roomname":"lobby"},{"username":"Eric","text":"he","roomname":"lobby"},{"username":"Eric","text":"he","roomname":"lobby"},{"username":"Eric","text":"","roomname":"lobby"},{"username":"Eric","text":"hi!","roomname":"lobby"},{"username":"Eric","text":"hi!","roomname":"lobby"},{"username":"Eric","text":"mememem","roomname":"hi"}]}